rockface/__init__.py
rockface/client.py
rockface/py.typed
rockface/rig.py
rockface/rpc.py
rockface/api/__init__.py
rockface/api/quantity.py
rockface/api/rig.py
rockface/api/rig_lock.py
rockface/api/tool_identity.py
rockface/api/tool_request.py
rockface/api/tools/__init__.py
rockface/api/tools/container.py
rockface/api/tools/gpio.py
rockface/api/tools/logic_analyser.py
rockface/api/tools/psu.py
rockface/api/tools/usb_serial.py
rockface/dev/__init__.py
rockface/dev/feature_flags.py
rockface/tools/__init__.py
rockface/tools/container.py
rockface/tools/gpio.py
rockface/tools/logic_analyser.py
rockface/tools/programmer.py
rockface/tools/psu.py
rockface/tools/usb_serial.py
rockface-0.89.0.dist-info/LICENSE
rockface-0.89.0.dist-info/METADATA
rockface-0.89.0.dist-info/WHEEL
rockface-0.89.0.dist-info/top_level.txt
rockface-0.89.0.dist-info/RECORD
